Workbook

Sheet Start_Here
A1: AI MUNIM - FORECAST AND CASH PLAN v2 (corrected to the canonical Oct 27 deck/wireframe numbers)
A2: ALL DATA SYNTHETIC. Lenders generic and simulated. No real Paytm/bank/lender figures.
A4: HOW THIS WORKBOOK FOLLOWS YOUR STANDARD
A5: - Blue cells (Inputs, Outflows, Policies) are the only raw inputs. History rows are SIMULATED raw observations,
A6: standing in for imported settlement data - they are inputs, not calculations.
A7: - Every derived number is a native Excel formula: AVERAGEIFS (forecast), SUMIFS (daily outflows),
A8: PMT (loan EMIs), running balances, MIN/INDEX/MATCH (option summaries). Change an input and it recalculates.
A9: - The prior pasted-Python Holt-Winters forecast is REPLACED by a formula-native method: per-outlet 12-week
A10: same-weekday average, with the festival week multiplied by the uplift inputs (1.8x Dadar, 1.5x others).
A11: This matches the deck design parameter D6 (last 12 weeks + last year festival pattern). It is not Holt-Winters.
A13: TWO COLLECTION COLUMNS, ON PURPOSE
A14: - collections_screen_rate: the rates stated on the cash-plan screen (70,000/day, 1.2 lakh/day festival).
... A31: contractual 3-EMI quote (68,733/month; 4 Dec and 4 Jan fall inside the window; 4 Feb outside).

Sheet Inputs
A1: AI MUNIM - INPUTS (blue = change me; everything derived recalculates)
A2: All figures SYNTHETIC. Lenders generic and simulated. Canonical source: Oct 27 deck/wireframes.
A3: opening_cash_30oct | B3: 450000
A4: as_of | B4: 46325
A5: plan_days | B5: 90
A6: uplift_dadar | B6: 1.8
A7: uplift_others | B7: 1.5
A8: festival_start | B8: 46330
A9: festival_end | B9: 46334
A10: forecast_training_days | B10: 84
A11: screen_rate_normal_per_day | B11: 70000
A12: screen_rate_festival_per_day | B12: 120000
A13: credit_cap_ratio_of_avg_daily_collections | B13: 0.08
A14: avg_MONTHLY_collections_for_cap (deck-stated Rs19 lakh) | B14: 1900000
... A27: existing_emi_first_due (ASSUMED date - NOT a source fact; then monthly same day) | B27: 46327

Sheet History_DAD
A1: date | B1: weekday (formula) | C1: collections_inr (SIMULATED RAW INPUT - all channels)
A2: 45778 | B2: =WEEKDAY(A2,1) -> 5 | C2: 33471
A3: 45779 | B3: =WEEKDAY(A3,1) -> 6 | C3: 34519
A4: 45780 | B4: =WEEKDAY(A4,1) -> 7 | C4: 38451
A5: 45781 | B5: =WEEKDAY(A5,1) -> 1 | C5: 33731
A6: 45782 | B6: =WEEKDAY(A6,1) -> 2 | C6: 31413
A7: 45783 | B7: =WEEKDAY(A7,1) -> 3 | C7: 31928
A8: 45784 | B8: =WEEKDAY(A8,1) -> 4 | C8: 32078
A9: 45785 | B9: =WEEKDAY(A9,1) -> 5 | C9: 32757
A10: 45786 | B10: =WEEKDAY(A10,1) -> 6 | C10: 33934
A11: 45787 | B11: =WEEKDAY(A11,1) -> 7 | C11: 37121
A12: 45788 | B12: =WEEKDAY(A12,1) -> 1 | C12: 36394
A13: 45789 | B13: =WEEKDAY(A13,1) -> 2 | C13: 29848
... A548: 46324 | B548: =WEEKDAY(A548,1) -> 5 | C548: 35605

Sheet History_MAT
A1: date | B1: weekday (formula) | C1: collections_inr (SIMULATED RAW INPUT - all channels)
A2: 45778 | B2: =WEEKDAY(A2,1) -> 5 | C2: 18744
A3: 45779 | B3: =WEEKDAY(A3,1) -> 6 | C3: 19331
A4: 45780 | B4: =WEEKDAY(A4,1) -> 7 | C4: 21533
A5: 45781 | B5: =WEEKDAY(A5,1) -> 1 | C5: 18889
A6: 45782 | B6: =WEEKDAY(A6,1) -> 2 | C6: 17591
A7: 45783 | B7: =WEEKDAY(A7,1) -> 3 | C7: 17880
A8: 45784 | B8: =WEEKDAY(A8,1) -> 4 | C8: 17964
A9: 45785 | B9: =WEEKDAY(A9,1) -> 5 | C9: 18344
A10: 45786 | B10: =WEEKDAY(A10,1) -> 6 | C10: 19003
A11: 45787 | B11: =WEEKDAY(A11,1) -> 7 | C11: 20788
A12: 45788 | B12: =WEEKDAY(A12,1) -> 1 | C12: 20381
A13: 45789 | B13: =WEEKDAY(A13,1) -> 2 | C13: 16715
... A548: 46324 | B548: =WEEKDAY(A548,1) -> 5 | C548: 19939

Sheet History_SIO
A1: date | B1: weekday (formula) | C1: collections_inr (SIMULATED RAW INPUT - all channels)
A2: 45778 | B2: =WEEKDAY(A2,1) -> 5 | C2: 14727
A3: 45779 | B3: =WEEKDAY(A3,1) -> 6 | C3: 15188
A4: 45780 | B4: =WEEKDAY(A4,1) -> 7 | C4: 16919
A5: 45781 | B5: =WEEKDAY(A5,1) -> 1 | C5: 14842
A6: 45782 | B6: =WEEKDAY(A6,1) -> 2 | C6: 13822
A7: 45783 | B7: =WEEKDAY(A7,1) -> 3 | C7: 14048
A8: 45784 | B8: =WEEKDAY(A8,1) -> 4 | C8: 14114
A9: 45785 | B9: =WEEKDAY(A9,1) -> 5 | C9: 14413
A10: 45786 | B10: =WEEKDAY(A10,1) -> 6 | C10: 14931
A11: 45787 | B11: =WEEKDAY(A11,1) -> 7 | C11: 16333
A12: 45788 | B12: =WEEKDAY(A12,1) -> 1 | C12: 16013
A13: 45789 | B13: =WEEKDAY(A13,1) -> 2 | C13: 13133
... A548: 46324 | B548: =WEEKDAY(A548,1) -> 5 | C548: 15666

Sheet Forecast
A1: date | B1: DAD_avg12w | C1: MAT_avg12w | D1: SIO_avg12w | E1: DAD_fcst | F1: MAT_fcst | G1: SIO_fcst | H1: total_model | I1: screen_rate
A2: 46325 | B2: =AVERAGEIFS(History_DAD!$C$2:$C$548,History_DAD!$B$2:$B$548,WEEKDAY($A2,1),History_DAD!$A$2:$A$548,">="&(Inputs!$B$4-Inputs!$B$10),History_DAD!$A$2:$A$548,"<"&Inputs!$B$4) -> 35801.583 | C2: =AVERAGEIFS(History_MAT!$C$2:$C$548,History_MAT!$B$2:$B$548,WEEKDAY($A2,1),History_MAT!$A$2:$A$548,">="&(Inputs!$B$4-Inputs!$B$10),History_MAT!$A$2:$A$548,"<"&Inputs!$B$4) -> 20049.083 | D2: =AVERAGEIFS(History_SIO!$C$2:$C$548,History_SIO!$B$2:$B$548,WEEKDAY($A2,1),History_SIO!$A$2:$A$548,">="&(Inputs!$B$4-Inputs!$B$10),History_SIO!$A$2:$A$548,"<"&Inputs!$B$4) -> 15752.75 | E2: =IF(AND($A2>=Inputs!$B$8,$A2<=Inputs!$B$9),B2*Inputs!$B$6,B2) -> 35801.583 | F2: =IF(AND($A2>=Inputs!$B$8,$A2<=Inputs!$B$9),C2*Inputs!$B$7,C2) -> 20049.083 | G2: =IF(AND($A2>=Inputs!$B$8,$A2<=Inputs!$B$9),D2*Inputs!$B$7,D2) -> 15752.75 | H2: =E2+F2+G2 -> 71603.417 | I2: =IF($A2<Inputs!$B$8,Inputs!$B$11,IF($A2<=Inputs!$B$9,Inputs!$B$12,Inputs!$B$11)) -> 70000
A3: 46326 | B3: =AVERAGEIFS(History_DAD!$C$2:$C$548,History_DAD!$B$2:$B$548,WEEKDAY($A3,1),History_DAD!$A$2:$A$548,">="&(Inputs!$B$4-Inputs!$B$10),History_DAD!$A$2:$A$548,"<"&Inputs!$B$4) -> 39113.333 | C3: =AVERAGEIFS(History_MAT!$C$2:$C$548,History_MAT!$B$2:$B$548,WEEKDAY($A3,1),History_MAT!$A$2:$A$548,">="&(Inputs!$B$4-Inputs!$B$10),History_MAT!$A$2:$A$548,"<"&Inputs!$B$4) -> 21903.333 | D3: =AVERAGEIFS(History_SIO!$C$2:$C$548,History_SIO!$B$2:$B$548,WEEKDAY($A3,1),History_SIO!$A$2:$A$548,">="&(Inputs!$B$4-Inputs!$B$10),History_SIO!$A$2:$A$548,"<"&Inputs!$B$4) -> 17209.917 | E3: =IF(AND($A3>=Inputs!$B$8,$A3<=Inputs!$B$9),B3*Inputs!$B$6,B3) -> 39113.333 | F3: =IF(AND($A3>=Inputs!$B$8,$A3<=Inputs!$B$9),C3*Inputs!$B$7,C3) -> 21903.333 | G3: =IF(AND($A3>=Inputs!$B$8,$A3<=Inputs!$B$9),D3*Inputs!$B$7,D3) -> 17209.917 | H3: =E3+F3+G3 -> 78226.583 | I3: =IF($A3<Inputs!$B$8,Inputs!$B$11,IF($A3<=Inputs!$B$9,Inputs!$B$12,Inputs!$B$11)) -> 70000
A4: 46327 | B4: =AVERAGEIFS(History_DAD!$C$2:$C$548,History_DAD!$B$2:$B$548,WEEKDAY($A4,1),History_DAD!$A$2:$A$548,">="&(Inputs!$B$4-Inputs!$B$10),History_DAD!$A$2:$A$548,"<"&Inputs!$B$4) -> 36355.5 | C4: =AVERAGEIFS(History_MAT!$C$2:$C$548,History_MAT!$B$2:$B$548,WEEKDAY($A4,1),History_MAT!$A$2:$A$548,">="&(Inputs!$B$4-Inputs!$B$10),History_MAT!$A$2:$A$548,"<"&Inputs!$B$4) -> 20359.167 | D4: =AVERAGEIFS(History_SIO!$C$2:$C$548,History_SIO!$B$2:$B$548,WEEKDAY($A4,1),History_SIO!$A$2:$A$548,">="&(Inputs!$B$4-Inputs!$B$10),History_SIO!$A$2:$A$548,"<"&Inputs!$B$4) -> 15996.333 | E4: =IF(AND($A4>=Inputs!$B$8,$A4<=Inputs!$B$9),B4*Inputs!$B$6,B4) -> 36355.5 | F4: =IF(AND($A4>=Inputs!$B$8,$A4<=Inputs!$B$9),C4*Inputs!$B$7,C4) -> 20359.167 | G4: =IF(AND($A4>=Inputs!$B$8,$A4<=Inputs!$B$9),D4*Inputs!$B$7,D4) -> 15996.333 | H4: =E4+F4+G4 -> 72711 | I4: =IF($A4<Inputs!$B$8,Inputs!$B$11,IF($A4<=Inputs!$B$9,Inputs!$B$12,Inputs!$B$11)) -> 70000
A5: 46328 | B5: =AVERAGEIFS(History_DAD!$C$2:$C$548,History_DAD!$B$2:$B$548,WEEKDAY($A5,1),History_DAD!$A$2:$A$548,">="&(Inputs!$B$4-Inputs!$B$10),History_DAD!$A$2:$A$548,"<"&Inputs!$B$4) -> 31997.333 | C5: =AVERAGEIFS(History_MAT!$C$2:$C$548,History_MAT!$B$2:$B$548,WEEKDAY($A5,1),History_MAT!$A$2:$A$548,">="&(Inputs!$B$4-Inputs!$B$10),History_MAT!$A$2:$A$548,"<"&Inputs!$B$4) -> 17918.5 | D5: =AVERAGEIFS(History_SIO!$C$2:$C$548,History_SIO!$B$2:$B$548,WEEKDAY($A5,1),History_SIO!$A$2:$A$548,">="&(Inputs!$B$4-Inputs!$B$10),History_SIO!$A$2:$A$548,"<"&Inputs!$B$4) -> 14078.833 | E5: =IF(AND($A5>=Inputs!$B$8,$A5<=Inputs!$B$9),B5*Inputs!$B$6,B5) -> 31997.333 | F5: =IF(AND($A5>=Inputs!$B$8,$A5<=Inputs!$B$9),C5*Inputs!$B$7,C5) -> 17918.5 | G5: =IF(AND($A5>=Inputs!$B$8,$A5<=Inputs!$B$9),D5*Inputs!$B$7,D5) -> 14078.833 | H5: =E5+F5+G5 -> 63994.667 | I5: =IF($A5<Inputs!$B$8,Inputs!$B$11,IF($A5<=Inputs!$B$9,Inputs!$B$12,Inputs!$B$11)) -> 70000
A6: 46329 | B6: =AVERAGEIFS(History_DAD!$C$2:$C$548,History_DAD!$B$2:$B$548,WEEKDAY($A6,1),History_DAD!$A$2:$A$548,">="&(Inputs!$B$4-Inputs!$B$10),History_DAD!$A$2:$A$548,"<"&Inputs!$B$4) -> 33193.5 | C6: =AVERAGEIFS(History_MAT!$C$2:$C$548,History_MAT!$B$2:$B$548,WEEKDAY($A6,1),History_MAT!$A$2:$A$548,">="&(Inputs!$B$4-Inputs!$B$10),History_MAT!$A$2:$A$548,"<"&Inputs!$B$4) -> 18588.25 | D6: =AVERAGEIFS(History_SIO!$C$2:$C$548,History_SIO!$B$2:$B$548,WEEKDAY($A6,1),History_SIO!$A$2:$A$548,">="&(Inputs!$B$4-Inputs!$B$10),History_SIO!$A$2:$A$548,"<"&Inputs!$B$4) -> 14605.167 | E6: =IF(AND($A6>=Inputs!$B$8,$A6<=Inputs!$B$9),B6*Inputs!$B$6,B6) -> 33193.5 | F6: =IF(AND($A6>=Inputs!$B$8,$A6<=Inputs!$B$9),C6*Inputs!$B$7,C6) -> 18588.25 | G6: =IF(AND($A6>=Inputs!$B$8,$A6<=Inputs!$B$9),D6*Inputs!$B$7,D6) -> 14605.167 | H6: =E6+F6+G6 -> 66386.917 | I6: =IF($A6<Inputs!$B$8,Inputs!$B$11,IF($A6<=Inputs!$B$9,Inputs!$B$12,Inputs!$B$11)) -> 70000
A7: 46330 | B7: =AVERAGEIFS(History_DAD!$C$2:$C$548,History_DAD!$B$2:$B$548,WEEKDAY($A7,1),History_DAD!$A$2:$A$548,">="&(Inputs!$B$4-Inputs!$B$10),History_DAD!$A$2:$A$548,"<"&Inputs!$B$4) -> 34045.833 | C7: =AVERAGEIFS(History_MAT!$C$2:$C$548,History_MAT!$B$2:$B$548,WEEKDAY($A7,1),History_MAT!$A$2:$A$548,">="&(Inputs!$B$4-Inputs!$B$10),History_MAT!$A$2:$A$548,"<"&Inputs!$B$4) -> 19065.583 | D7: =AVERAGEIFS(History_SIO!$C$2:$C$548,History_SIO!$B$2:$B$548,WEEKDAY($A7,1),History_SIO!$A$2:$A$548,">="&(Inputs!$B$4-Inputs!$B$10),History_SIO!$A$2:$A$548,"<"&Inputs!$B$4) -> 14980.167 | E7: =IF(AND($A7>=Inputs!$B$8,$A7<=Inputs!$B$9),B7*Inputs!$B$6,B7) -> 61282.5 | F7: =IF(AND($A7>=Inputs!$B$8,$A7<=Inputs!$B$9),C7*Inputs!$B$7,C7) -> 28598.375 | G7: =IF(AND($A7>=Inputs!$B$8,$A7<=Inputs!$B$9),D7*Inputs!$B$7,D7) -> 22470.25 | H7: =E7+F7+G7 -> 112351.12 | I7: =IF($A7<Inputs!$B$8,Inputs!$B$11,IF($A7<=Inputs!$B$9,Inputs!$B$12,Inputs!$B$11)) -> 120000
A8: 46331 | B8: =AVERAGEIFS(History_DAD!$C$2:$C$548,History_DAD!$B$2:$B$548,WEEKDAY($A8,1),History_DAD!$A$2:$A$548,">="&(Inputs!$B$4-Inputs!$B$10),History_DAD!$A$2:$A$548,"<"&Inputs!$B$4) -> 34997.667 | C8: =AVERAGEIFS(History_MAT!$C$2:$C$548,History_MAT!$B$2:$B$548,WEEKDAY($A8,1),History_MAT!$A$2:$A$548,">="&(Inputs!$B$4-Inputs!$B$10),History_MAT!$A$2:$A$548,"<"&Inputs!$B$4) -> 19598.75 | D8: =AVERAGEIFS(History_SIO!$C$2:$C$548,History_SIO!$B$2:$B$548,WEEKDAY($A8,1),History_SIO!$A$2:$A$548,">="&(Inputs!$B$4-Inputs!$B$10),History_SIO!$A$2:$A$548,"<"&Inputs!$B$4) -> 15398.917 | E8: =IF(AND($A8>=Inputs!$B$8,$A8<=Inputs!$B$9),B8*Inputs!$B$6,B8) -> 62995.8 | F8: =IF(AND($A8>=Inputs!$B$8,$A8<=Inputs!$B$9),C8*Inputs!$B$7,C8) -> 29398.125 | G8: =IF(AND($A8>=Inputs!$B$8,$A8<=Inputs!$B$9),D8*Inputs!$B$7,D8) -> 23098.375 | H8: =E8+F8+G8 -> 115492.3 | I8: =IF($A8<Inputs!$B$8,Inputs!$B$11,IF($A8<=Inputs!$B$9,Inputs!$B$12,Inputs!$B$11)) -> 120000
A9: 46332 | B9: =AVERAGEIFS(History_DAD!$C$2:$C$548,History_DAD!$B$2:$B$548,WEEKDAY($A9,1),History_DAD!$A$2:$A$548,">="&(Inputs!$B$4-Inputs!$B$10),History_DAD!$A$2:$A$548,"<"&Inputs!$B$4) -> 35801.583 | C9: =AVERAGEIFS(History_MAT!$C$2:$C$548,History_MAT!$B$2:$B$548,WEEKDAY($A9,1),History_MAT!$A$2:$A$548,">="&(Inputs!$B$4-Inputs!$B$10),History_MAT!$A$2:$A$548,"<"&Inputs!$B$4) -> 20049.083 | D9: =AVERAGEIFS(History_SIO!$C$2:$C$548,History_SIO!$B$2:$B$548,WEEKDAY($A9,1),History_SIO!$A$2:$A$548,">="&(Inputs!$B$4-Inputs!$B$10),History_SIO!$A$2:$A$548,"<"&Inputs!$B$4) -> 15752.75 | E9: =IF(AND($A9>=Inputs!$B$8,$A9<=Inputs!$B$9),B9*Inputs!$B$6,B9) -> 64442.85 | F9: =IF(AND($A9>=Inputs!$B$8,$A9<=Inputs!$B$9),C9*Inputs!$B$7,C9) -> 30073.625 | G9: =IF(AND($A9>=Inputs!$B$8,$A9<=Inputs!$B$9),D9*Inputs!$B$7,D9) -> 23629.125 | H9: =E9+F9+G9 -> 118145.6 | I9: =IF($A9<Inputs!$B$8,Inputs!$B$11,IF($A9<=Inputs!$B$9,Inputs!$B$12,Inputs!$B$11)) -> 120000
A10: 46333 | B10: =AVERAGEIFS(History_DAD!$C$2:$C$548,History_DAD!$B$2:$B$548,WEEKDAY($A10,1),History_DAD!$A$2:$A$548,">="&(Inputs!$B$4-Inputs!$B$10),History_DAD!$A$2:$A$548,"<"&Inputs!$B$4) -> 39113.333 | C10: =AVERAGEIFS(History_MAT!$C$2:$C$548,History_MAT!$B$2:$B$548,WEEKDAY($A10,1),History_MAT!$A$2:$A$548,">="&(Inputs!$B$4-Inputs!$B$10),History_MAT!$A$2:$A$548,"<"&Inputs!$B$4) -> 21903.333 | D10: =AVERAGEIFS(History_SIO!$C$2:$C$548,History_SIO!$B$2:$B$548,WEEKDAY($A10,1),History_SIO!$A$2:$A$548,">="&(Inputs!$B$4-Inputs!$B$10),History_SIO!$A$2:$A$548,"<"&Inputs!$B$4) -> 17209.917 | E10: =IF(AND($A10>=Inputs!$B$8,$A10<=Inputs!$B$9),B10*Inputs!$B$6,B10) -> 70404 | F10: =IF(AND($A10>=Inputs!$B$8,$A10<=Inputs!$B$9),C10*Inputs!$B$7,C10) -> 32855 | G10: =IF(AND($A10>=Inputs!$B$8,$A10<=Inputs!$B$9),D10*Inputs!$B$7,D10) -> 25814.875 | H10: =E10+F10+G10 -> 129073.88 | I10: =IF($A10<Inputs!$B$8,Inputs!$B$11,IF($A10<=Inputs!$B$9,Inputs!$B$12,Inputs!$B$11)) -> 120000
A11: 46334 | B11: =AVERAGEIFS(History_DAD!$C$2:$C$548,History_DAD!$B$2:$B$548,WEEKDAY($A11,1),History_DAD!$A$2:$A$548,">="&(Inputs!$B$4-Inputs!$B$10),History_DAD!$A$2:$A$548,"<"&Inputs!$B$4) -> 36355.5 | C11: =AVERAGEIFS(History_MAT!$C$2:$C$548,History_MAT!$B$2:$B$548,WEEKDAY($A11,1),History_MAT!$A$2:$A$548,">="&(Inputs!$B$4-Inputs!$B$10),History_MAT!$A$2:$A$548,"<"&Inputs!$B$4) -> 20359.167 | D11: =AVERAGEIFS(History_SIO!$C$2:$C$548,History_SIO!$B$2:$B$548,WEEKDAY($A11,1),History_SIO!$A$2:$A$548,">="&(Inputs!$B$4-Inputs!$B$10),History_SIO!$A$2:$A$548,"<"&Inputs!$B$4) -> 15996.333 | E11: =IF(AND($A11>=Inputs!$B$8,$A11<=Inputs!$B$9),B11*Inputs!$B$6,B11) -> 65439.9 | F11: =IF(AND($A11>=Inputs!$B$8,$A11<=Inputs!$B$9),C11*Inputs!$B$7,C11) -> 30538.75 | G11: =IF(AND($A11>=Inputs!$B$8,$A11<=Inputs!$B$9),D11*Inputs!$B$7,D11) -> 23994.5 | H11: =E11+F11+G11 -> 119973.15 | I11: =IF($A11<Inputs!$B$8,Inputs!$B$11,IF($A11<=Inputs!$B$9,Inputs!$B$12,Inputs!$B$11)) -> 120000
A12: 46335 | B12: =AVERAGEIFS(History_DAD!$C$2:$C$548,History_DAD!$B$2:$B$548,WEEKDAY($A12,1),History_DAD!$A$2:$A$548,">="&(Inputs!$B$4-Inputs!$B$10),History_DAD!$A$2:$A$548,"<"&Inputs!$B$4) -> 31997.333 | C12: =AVERAGEIFS(History_MAT!$C$2:$C$548,History_MAT!$B$2:$B$548,WEEKDAY($A12,1),History_MAT!$A$2:$A$548,">="&(Inputs!$B$4-Inputs!$B$10),History_MAT!$A$2:$A$548,"<"&Inputs!$B$4) -> 17918.5 | D12: =AVERAGEIFS(History_SIO!$C$2:$C$548,History_SIO!$B$2:$B$548,WEEKDAY($A12,1),History_SIO!$A$2:$A$548,">="&(Inputs!$B$4-Inputs!$B$10),History_SIO!$A$2:$A$548,"<"&Inputs!$B$4) -> 14078.833 | E12: =IF(AND($A12>=Inputs!$B$8,$A12<=Inputs!$B$9),B12*Inputs!$B$6,B12) -> 31997.333 | F12: =IF(AND($A12>=Inputs!$B$8,$A12<=Inputs!$B$9),C12*Inputs!$B$7,C12) -> 17918.5 | G12: =IF(AND($A12>=Inputs!$B$8,$A12<=Inputs!$B$9),D12*Inputs!$B$7,D12) -> 14078.833 | H12: =E12+F12+G12 -> 63994.667 | I12: =IF($A12<Inputs!$B$8,Inputs!$B$11,IF($A12<=Inputs!$B$9,Inputs!$B$12,Inputs!$B$11)) -> 70000
A13: 46336 | B13: =AVERAGEIFS(History_DAD!$C$2:$C$548,History_DAD!$B$2:$B$548,WEEKDAY($A13,1),History_DAD!$A$2:$A$548,">="&(Inputs!$B$4-Inputs!$B$10),History_DAD!$A$2:$A$548,"<"&Inputs!$B$4) -> 33193.5 | C13: =AVERAGEIFS(History_MAT!$C$2:$C$548,History_MAT!$B$2:$B$548,WEEKDAY($A13,1),History_MAT!$A$2:$A$548,">="&(Inputs!$B$4-Inputs!$B$10),History_MAT!$A$2:$A$548,"<"&Inputs!$B$4) -> 18588.25 | D13: =AVERAGEIFS(History_SIO!$C$2:$C$548,History_SIO!$B$2:$B$548,WEEKDAY($A13,1),History_SIO!$A$2:$A$548,">="&(Inputs!$B$4-Inputs!$B$10),History_SIO!$A$2:$A$548,"<"&Inputs!$B$4) -> 14605.167 | E13: =IF(AND($A13>=Inputs!$B$8,$A13<=Inputs!$B$9),B13*Inputs!$B$6,B13) -> 33193.5 | F13: =IF(AND($A13>=Inputs!$B$8,$A13<=Inputs!$B$9),C13*Inputs!$B$7,C13) -> 18588.25 | G13: =IF(AND($A13>=Inputs!$B$8,$A13<=Inputs!$B$9),D13*Inputs!$B$7,D13) -> 14605.167 | H13: =E13+F13+G13 -> 66386.917 | I13: =IF($A13<Inputs!$B$8,Inputs!$B$11,IF($A13<=Inputs!$B$9,Inputs!$B$12,Inputs!$B$11)) -> 70000
... A91: 46414 | B91: =AVERAGEIFS(History_DAD!$C$2:$C$548,History_DAD!$B$2:$B$548,WEEKDAY($A91,1),History_DAD!$A$2:$A$548,">="&(Inputs!$B$4-Inputs!$B$10),History_DAD!$A$2:$A$548,"<"&Inputs!$B$4) -> 34045.833 | C91: =AVERAGEIFS(History_MAT!$C$2:$C$548,History_MAT!$B$2:$B$548,WEEKDAY($A91,1),History_MAT!$A$2:$A$548,">="&(Inputs!$B$4-Inputs!$B$10),History_MAT!$A$2:$A$548,"<"&Inputs!$B$4) -> 19065.583 | D91: =AVERAGEIFS(History_SIO!$C$2:$C$548,History_SIO!$B$2:$B$548,WEEKDAY($A91,1),History_SIO!$A$2:$A$548,">="&(Inputs!$B$4-Inputs!$B$10),History_SIO!$A$2:$A$548,"<"&Inputs!$B$4) -> 14980.167 | E91: =IF(AND($A91>=Inputs!$B$8,$A91<=Inputs!$B$9),B91*Inputs!$B$6,B91) -> 34045.833 | F91: =IF(AND($A91>=Inputs!$B$8,$A91<=Inputs!$B$9),C91*Inputs!$B$7,C91) -> 19065.583 | G91: =IF(AND($A91>=Inputs!$B$8,$A91<=Inputs!$B$9),D91*Inputs!$B$7,D91) -> 14980.167 | H91: =E91+F91+G91 -> 68091.583 | I91: =IF($A91<Inputs!$B$8,Inputs!$B$11,IF($A91<=Inputs!$B$9,Inputs!$B$12,Inputs!$B$11)) -> 70000

Sheet Outflows
A1: id | B1: date | C1: payee | D1: category | E1: amount_inr (INPUT) | F1: note
A2: STOCK-PATEL | B2: 46326 | C2: Patel Traders | D2: festival_stock | E2: 290000 | F2: canonical
A3: SAL-11 | B3: 46327 | C3: Staff pool (7 staff) | D3: salaries | E3: 105000 | F3: canonical
A4: STOCK-MEHTA | B4: 46327 | C4: Mehta Dry Fruits | D4: festival_stock | E4: 150000 | F4: canonical
A5: STOCK-GUPTA | B5: 46330 | C5: Gupta Distributors | D5: festival_stock | E5: 520000 | F5: canonical - invoice GD-1182
A6: RENT-11 | B6: 46331 | C6: Landlord (3 outlets) | D6: rent | E6: 107000 | F6: canonical
A7: BONUS-11 | B7: 46331 | C7: Staff pool | D7: diwali_bonus | E7: 52500 | F7: canonical
A8: GST-11 | B8: 46346 | C8: GST (October) | D8: gst | E8: 42000 | F8: canonical
A9: SAL-12 | B9: 46357 | C9: Staff pool (7 staff) | D9: salaries | E9: 105000 | F9: ASSUMED recurring bill; actual bills beyond the canonical list are unknown
A10: RENT-12 | B10: 46361 | C10: Landlord (3 outlets) | D10: rent | E10: 107000 | F10: ASSUMED recurring bill; actual bills beyond the canonical list are unknown
A11: GST-12 | B11: 46376 | C11: GST (November) | D11: gst | E11: 42000 | F11: ASSUMED recurring bill; actual bills beyond the canonical list are unknown
A12: SAL-01 | B12: 46388 | C12: Staff pool (7 staff) | D12: salaries | E12: 105000 | F12: ASSUMED recurring bill; actual bills beyond the canonical list are unknown
A13: RENT-01 | B13: 46392 | C13: Landlord (3 outlets) | D13: rent | E13: 107000 | F13: ASSUMED recurring bill; actual bills beyond the canonical list are unknown
... A18: EXISTING-EMI-01 | B18: 46388 | C18: Existing lender (simulated) | D18: existing_emi_assumed | E18: 22000 | F18: ASSUMED due date (1st monthly) - NOT in the deck Coming-Up list; model columns only

Sheet Daily_Cash
A1: date | B1: outflows | C1: emi_assumed | D1: coll_screen | E1: coll_model | F1: bal_story_PART | G1: bal_model | H1: story+drawdn | I1: story+defer | J1: story+buyless_P | K1: model+drawdn | L1: repay30_story | M1: repay30_model | O1: READ ME: bal_story_PARTIAL reproduces the deck screen narrative from its stated rates and listed bills ONLY (no existing EMI, no unlisted bills) - an ILLUSTRATIVE ANCHOR, not a validated cash forecast. bal_model = formula forecast from 18-month history INCLUDING the assumed existing EMI (1st monthly, editable Inputs B27). Every scenario appears on BOTH bases. Two repayment paths are distinct: EMI plan (contractual 3 x EMI, deducted 4 Dec / 4 Jan) vs repay-in-full 30 Nov (principal + 26-day interest estimate deducted once, no EMIs). Buy-less is PARTIAL cover and is labeled as such. Drawdown = supplier-direct net relief once (Rs3.2L merchant cash + Rs2L lender-paid to Gupta).
A2: =Forecast!A2 -> 46325 | B2: =SUMIFS(Outflows!$E$2:$E$18,Outflows!$B$2:$B$18,$A2,Outflows!$D$2:$D$18,"<>existing_emi_assumed") -> 0 | C2: =SUMIFS(Outflows!$E$2:$E$18,Outflows!$B$2:$B$18,$A2,Outflows!$D$2:$D$18,"existing_emi_assumed") -> 0 | D2: =Forecast!I2 -> 70000 | E2: =Forecast!H2 -> 71603.417 | F2: =Inputs!$B$3+D2-B2 -> 520000 | G2: =Inputs!$B$3+E2-B2-C2 -> 521603.42 | H2: =F2+IF($A2>=Inputs!$B$21,Inputs!$B$20,0)-IF($A2>=DATE(2026,12,4),Loan_Schedule!$B$4,0)-IF($A2>=DATE(2027,1,4),Loan_Schedule!$B$4,0) -> 520000 | I2: =F2+IF(AND($A2>=Inputs!$B$21,$A2<Inputs!$B$23),Inputs!$B$22,0) -> 520000 | J2: =F2+(Inputs!$B$26/Inputs!$B$25)*(IF($A2>=DATE(2026,10,31),290000,0)+IF($A2>=DATE(2026,11,1),150000,0)+IF($A2>=DATE(2026,11,4),520000,0)) -> 520000 | K2: =G2+IF($A2>=Inputs!$B$21,Inputs!$B$20,0)-IF($A2>=DATE(2026,12,4),Loan_Schedule!$B$4,0)-IF($A2>=DATE(2027,1,4),Loan_Schedule!$B$4,0) -> 521603.42 | L2: =F2+IF($A2>=Inputs!$B$21,Inputs!$B$20,0)-IF($A2>=DATE(2026,11,30),Inputs!$B$20+Loan_Schedule!$B$7,0) -> 520000 | M2: =G2+IF($A2>=Inputs!$B$21,Inputs!$B$20,0)-IF($A2>=DATE(2026,11,30),Inputs!$B$20+Loan_Schedule!$B$7,0) -> 521603.42
A3: =Forecast!A3 -> 46326 | B3: =SUMIFS(Outflows!$E$2:$E$18,Outflows!$B$2:$B$18,$A3,Outflows!$D$2:$D$18,"<>existing_emi_assumed") -> 290000 | C3: =SUMIFS(Outflows!$E$2:$E$18,Outflows!$B$2:$B$18,$A3,Outflows!$D$2:$D$18,"existing_emi_assumed") -> 0 | D3: =Forecast!I3 -> 70000 | E3: =Forecast!H3 -> 78226.583 | F3: =F2+D3-B3 -> 300000 | G3: =G2+E3-B3-C3 -> 309830 | H3: =F3+IF($A3>=Inputs!$B$21,Inputs!$B$20,0)-IF($A3>=DATE(2026,12,4),Loan_Schedule!$B$4,0)-IF($A3>=DATE(2027,1,4),Loan_Schedule!$B$4,0) -> 300000 | I3: =F3+IF(AND($A3>=Inputs!$B$21,$A3<Inputs!$B$23),Inputs!$B$22,0) -> 300000 | J3: =F3+(Inputs!$B$26/Inputs!$B$25)*(IF($A3>=DATE(2026,10,31),290000,0)+IF($A3>=DATE(2026,11,1),150000,0)+IF($A3>=DATE(2026,11,4),520000,0)) -> 354375 | K3: =G3+IF($A3>=Inputs!$B$21,Inputs!$B$20,0)-IF($A3>=DATE(2026,12,4),Loan_Schedule!$B$4,0)-IF($A3>=DATE(2027,1,4),Loan_Schedule!$B$4,0) -> 309830 | L3: =F3+IF($A3>=Inputs!$B$21,Inputs!$B$20,0)-IF($A3>=DATE(2026,11,30),Inputs!$B$20+Loan_Schedule!$B$7,0) -> 300000 | M3: =G3+IF($A3>=Inputs!$B$21,Inputs!$B$20,0)-IF($A3>=DATE(2026,11,30),Inputs!$B$20+Loan_Schedule!$B$7,0) -> 309830
A4: =Forecast!A4 -> 46327 | B4: =SUMIFS(Outflows!$E$2:$E$18,Outflows!$B$2:$B$18,$A4,Outflows!$D$2:$D$18,"<>existing_emi_assumed") -> 255000 | C4: =SUMIFS(Outflows!$E$2:$E$18,Outflows!$B$2:$B$18,$A4,Outflows!$D$2:$D$18,"existing_emi_assumed") -> 22000 | D4: =Forecast!I4 -> 70000 | E4: =Forecast!H4 -> 72711 | F4: =F3+D4-B4 -> 115000 | G4: =G3+E4-B4-C4 -> 105541 | H4: =F4+IF($A4>=Inputs!$B$21,Inputs!$B$20,0)-IF($A4>=DATE(2026,12,4),Loan_Schedule!$B$4,0)-IF($A4>=DATE(2027,1,4),Loan_Schedule!$B$4,0) -> 115000 | I4: =F4+IF(AND($A4>=Inputs!$B$21,$A4<Inputs!$B$23),Inputs!$B$22,0) -> 115000 | J4: =F4+(Inputs!$B$26/Inputs!$B$25)*(IF($A4>=DATE(2026,10,31),290000,0)+IF($A4>=DATE(2026,11,1),150000,0)+IF($A4>=DATE(2026,11,4),520000,0)) -> 197500 | K4: =G4+IF($A4>=Inputs!$B$21,Inputs!$B$20,0)-IF($A4>=DATE(2026,12,4),Loan_Schedule!$B$4,0)-IF($A4>=DATE(2027,1,4),Loan_Schedule!$B$4,0) -> 105541 | L4: =F4+IF($A4>=Inputs!$B$21,Inputs!$B$20,0)-IF($A4>=DATE(2026,11,30),Inputs!$B$20+Loan_Schedule!$B$7,0) -> 115000 | M4: =G4+IF($A4>=Inputs!$B$21,Inputs!$B$20,0)-IF($A4>=DATE(2026,11,30),Inputs!$B$20+Loan_Schedule!$B$7,0) -> 105541
A5: =Forecast!A5 -> 46328 | B5: =SUMIFS(Outflows!$E$2:$E$18,Outflows!$B$2:$B$18,$A5,Outflows!$D$2:$D$18,"<>existing_emi_assumed") -> 0 | C5: =SUMIFS(Outflows!$E$2:$E$18,Outflows!$B$2:$B$18,$A5,Outflows!$D$2:$D$18,"existing_emi_assumed") -> 0 | D5: =Forecast!I5 -> 70000 | E5: =Forecast!H5 -> 63994.667 | F5: =F4+D5-B5 -> 185000 | G5: =G4+E5-B5-C5 -> 169535.67 | H5: =F5+IF($A5>=Inputs!$B$21,Inputs!$B$20,0)-IF($A5>=DATE(2026,12,4),Loan_Schedule!$B$4,0)-IF($A5>=DATE(2027,1,4),Loan_Schedule!$B$4,0) -> 185000 | I5: =F5+IF(AND($A5>=Inputs!$B$21,$A5<Inputs!$B$23),Inputs!$B$22,0) -> 185000 | J5: =F5+(Inputs!$B$26/Inputs!$B$25)*(IF($A5>=DATE(2026,10,31),290000,0)+IF($A5>=DATE(2026,11,1),150000,0)+IF($A5>=DATE(2026,11,4),520000,0)) -> 267500 | K5: =G5+IF($A5>=Inputs!$B$21,Inputs!$B$20,0)-IF($A5>=DATE(2026,12,4),Loan_Schedule!$B$4,0)-IF($A5>=DATE(2027,1,4),Loan_Schedule!$B$4,0) -> 169535.67 | L5: =F5+IF($A5>=Inputs!$B$21,Inputs!$B$20,0)-IF($A5>=DATE(2026,11,30),Inputs!$B$20+Loan_Schedule!$B$7,0) -> 185000 | M5: =G5+IF($A5>=Inputs!$B$21,Inputs!$B$20,0)-IF($A5>=DATE(2026,11,30),Inputs!$B$20+Loan_Schedule!$B$7,0) -> 169535.67
A6: =Forecast!A6 -> 46329 | B6: =SUMIFS(Outflows!$E$2:$E$18,Outflows!$B$2:$B$18,$A6,Outflows!$D$2:$D$18,"<>existing_emi_assumed") -> 0 | C6: =SUMIFS(Outflows!$E$2:$E$18,Outflows!$B$2:$B$18,$A6,Outflows!$D$2:$D$18,"existing_emi_assumed") -> 0 | D6: =Forecast!I6 -> 70000 | E6: =Forecast!H6 -> 66386.917 | F6: =F5+D6-B6 -> 255000 | G6: =G5+E6-B6-C6 -> 235922.58 | H6: =F6+IF($A6>=Inputs!$B$21,Inputs!$B$20,0)-IF($A6>=DATE(2026,12,4),Loan_Schedule!$B$4,0)-IF($A6>=DATE(2027,1,4),Loan_Schedule!$B$4,0) -> 255000 | I6: =F6+IF(AND($A6>=Inputs!$B$21,$A6<Inputs!$B$23),Inputs!$B$22,0) -> 255000 | J6: =F6+(Inputs!$B$26/Inputs!$B$25)*(IF($A6>=DATE(2026,10,31),290000,0)+IF($A6>=DATE(2026,11,1),150000,0)+IF($A6>=DATE(2026,11,4),520000,0)) -> 337500 | K6: =G6+IF($A6>=Inputs!$B$21,Inputs!$B$20,0)-IF($A6>=DATE(2026,12,4),Loan_Schedule!$B$4,0)-IF($A6>=DATE(2027,1,4),Loan_Schedule!$B$4,0) -> 235922.58 | L6: =F6+IF($A6>=Inputs!$B$21,Inputs!$B$20,0)-IF($A6>=DATE(2026,11,30),Inputs!$B$20+Loan_Schedule!$B$7,0) -> 255000 | M6: =G6+IF($A6>=Inputs!$B$21,Inputs!$B$20,0)-IF($A6>=DATE(2026,11,30),Inputs!$B$20+Loan_Schedule!$B$7,0) -> 235922.58
A7: =Forecast!A7 -> 46330 | B7: =SUMIFS(Outflows!$E$2:$E$18,Outflows!$B$2:$B$18,$A7,Outflows!$D$2:$D$18,"<>existing_emi_assumed") -> 520000 | C7: =SUMIFS(Outflows!$E$2:$E$18,Outflows!$B$2:$B$18,$A7,Outflows!$D$2:$D$18,"existing_emi_assumed") -> 0 | D7: =Forecast!I7 -> 120000 | E7: =Forecast!H7 -> 112351.12 | F7: =F6+D7-B7 -> -145000 | G7: =G6+E7-B7-C7 -> -171726.29 | H7: =F7+IF($A7>=Inputs!$B$21,Inputs!$B$20,0)-IF($A7>=DATE(2026,12,4),Loan_Schedule!$B$4,0)-IF($A7>=DATE(2027,1,4),Loan_Schedule!$B$4,0) -> 55000 | I7: =F7+IF(AND($A7>=Inputs!$B$21,$A7<Inputs!$B$23),Inputs!$B$22,0) -> 55000 | J7: =F7+(Inputs!$B$26/Inputs!$B$25)*(IF($A7>=DATE(2026,10,31),290000,0)+IF($A7>=DATE(2026,11,1),150000,0)+IF($A7>=DATE(2026,11,4),520000,0)) -> 35000 | K7: =G7+IF($A7>=Inputs!$B$21,Inputs!$B$20,0)-IF($A7>=DATE(2026,12,4),Loan_Schedule!$B$4,0)-IF($A7>=DATE(2027,1,4),Loan_Schedule!$B$4,0) -> 28273.708 | L7: =F7+IF($A7>=Inputs!$B$21,Inputs!$B$20,0)-IF($A7>=DATE(2026,11,30),Inputs!$B$20+Loan_Schedule!$B$7,0) -> 55000 | M7: =G7+IF($A7>=Inputs!$B$21,Inputs!$B$20,0)-IF($A7>=DATE(2026,11,30),Inputs!$B$20+Loan_Schedule!$B$7,0) -> 28273.708
A8: =Forecast!A8 -> 46331 | B8: =SUMIFS(Outflows!$E$2:$E$18,Outflows!$B$2:$B$18,$A8,Outflows!$D$2:$D$18,"<>existing_emi_assumed") -> 159500 | C8: =SUMIFS(Outflows!$E$2:$E$18,Outflows!$B$2:$B$18,$A8,Outflows!$D$2:$D$18,"existing_emi_assumed") -> 0 | D8: =Forecast!I8 -> 120000 | E8: =Forecast!H8 -> 115492.3 | F8: =F7+D8-B8 -> -184500 | G8: =G7+E8-B8-C8 -> -215733.99 | H8: =F8+IF($A8>=Inputs!$B$21,Inputs!$B$20,0)-IF($A8>=DATE(2026,12,4),Loan_Schedule!$B$4,0)-IF($A8>=DATE(2027,1,4),Loan_Schedule!$B$4,0) -> 15500 | I8: =F8+IF(AND($A8>=Inputs!$B$21,$A8<Inputs!$B$23),Inputs!$B$22,0) -> 15500 | J8: =F8+(Inputs!$B$26/Inputs!$B$25)*(IF($A8>=DATE(2026,10,31),290000,0)+IF($A8>=DATE(2026,11,1),150000,0)+IF($A8>=DATE(2026,11,4),520000,0)) -> -4500 | K8: =G8+IF($A8>=Inputs!$B$21,Inputs!$B$20,0)-IF($A8>=DATE(2026,12,4),Loan_Schedule!$B$4,0)-IF($A8>=DATE(2027,1,4),Loan_Schedule!$B$4,0) -> -15733.992 | L8: =F8+IF($A8>=Inputs!$B$21,Inputs!$B$20,0)-IF($A8>=DATE(2026,11,30),Inputs!$B$20+Loan_Schedule!$B$7,0) -> 15500 | M8: =G8+IF($A8>=Inputs!$B$21,Inputs!$B$20,0)-IF($A8>=DATE(2026,11,30),Inputs!$B$20+Loan_Schedule!$B$7,0) -> -15733.992
A9: =Forecast!A9 -> 46332 | B9: =SUMIFS(Outflows!$E$2:$E$18,Outflows!$B$2:$B$18,$A9,Outflows!$D$2:$D$18,"<>existing_emi_assumed") -> 0 | C9: =SUMIFS(Outflows!$E$2:$E$18,Outflows!$B$2:$B$18,$A9,Outflows!$D$2:$D$18,"existing_emi_assumed") -> 0 | D9: =Forecast!I9 -> 120000 | E9: =Forecast!H9 -> 118145.6 | F9: =F8+D9-B9 -> -64500 | G9: =G8+E9-B9-C9 -> -97588.392 | H9: =F9+IF($A9>=Inputs!$B$21,Inputs!$B$20,0)-IF($A9>=DATE(2026,12,4),Loan_Schedule!$B$4,0)-IF($A9>=DATE(2027,1,4),Loan_Schedule!$B$4,0) -> 135500 | I9: =F9+IF(AND($A9>=Inputs!$B$21,$A9<Inputs!$B$23),Inputs!$B$22,0) -> 135500 | J9: =F9+(Inputs!$B$26/Inputs!$B$25)*(IF($A9>=DATE(2026,10,31),290000,0)+IF($A9>=DATE(2026,11,1),150000,0)+IF($A9>=DATE(2026,11,4),520000,0)) -> 115500 | K9: =G9+IF($A9>=Inputs!$B$21,Inputs!$B$20,0)-IF($A9>=DATE(2026,12,4),Loan_Schedule!$B$4,0)-IF($A9>=DATE(2027,1,4),Loan_Schedule!$B$4,0) -> 102411.61 | L9: =F9+IF($A9>=Inputs!$B$21,Inputs!$B$20,0)-IF($A9>=DATE(2026,11,30),Inputs!$B$20+Loan_Schedule!$B$7,0) -> 135500 | M9: =G9+IF($A9>=Inputs!$B$21,Inputs!$B$20,0)-IF($A9>=DATE(2026,11,30),Inputs!$B$20+Loan_Schedule!$B$7,0) -> 102411.61
A10: =Forecast!A10 -> 46333 | B10: =SUMIFS(Outflows!$E$2:$E$18,Outflows!$B$2:$B$18,$A10,Outflows!$D$2:$D$18,"<>existing_emi_assumed") -> 0 | C10: =SUMIFS(Outflows!$E$2:$E$18,Outflows!$B$2:$B$18,$A10,Outflows!$D$2:$D$18,"existing_emi_assumed") -> 0 | D10: =Forecast!I10 -> 120000 | E10: =Forecast!H10 -> 129073.88 | F10: =F9+D10-B10 -> 55500 | G10: =G9+E10-B10-C10 -> 31485.483 | H10: =F10+IF($A10>=Inputs!$B$21,Inputs!$B$20,0)-IF($A10>=DATE(2026,12,4),Loan_Schedule!$B$4,0)-IF($A10>=DATE(2027,1,4),Loan_Schedule!$B$4,0) -> 255500 | I10: =F10+IF(AND($A10>=Inputs!$B$21,$A10<Inputs!$B$23),Inputs!$B$22,0) -> 255500 | J10: =F10+(Inputs!$B$26/Inputs!$B$25)*(IF($A10>=DATE(2026,10,31),290000,0)+IF($A10>=DATE(2026,11,1),150000,0)+IF($A10>=DATE(2026,11,4),520000,0)) -> 235500 | K10: =G10+IF($A10>=Inputs!$B$21,Inputs!$B$20,0)-IF($A10>=DATE(2026,12,4),Loan_Schedule!$B$4,0)-IF($A10>=DATE(2027,1,4),Loan_Schedule!$B$4,0) -> 231485.48 | L10: =F10+IF($A10>=Inputs!$B$21,Inputs!$B$20,0)-IF($A10>=DATE(2026,11,30),Inputs!$B$20+Loan_Schedule!$B$7,0) -> 255500 | M10: =G10+IF($A10>=Inputs!$B$21,Inputs!$B$20,0)-IF($A10>=DATE(2026,11,30),Inputs!$B$20+Loan_Schedule!$B$7,0) -> 231485.48
A11: =Forecast!A11 -> 46334 | B11: =SUMIFS(Outflows!$E$2:$E$18,Outflows!$B$2:$B$18,$A11,Outflows!$D$2:$D$18,"<>existing_emi_assumed") -> 0 | C11: =SUMIFS(Outflows!$E$2:$E$18,Outflows!$B$2:$B$18,$A11,Outflows!$D$2:$D$18,"existing_emi_assumed") -> 0 | D11: =Forecast!I11 -> 120000 | E11: =Forecast!H11 -> 119973.15 | F11: =F10+D11-B11 -> 175500 | G11: =G10+E11-B11-C11 -> 151458.63 | H11: =F11+IF($A11>=Inputs!$B$21,Inputs!$B$20,0)-IF($A11>=DATE(2026,12,4),Loan_Schedule!$B$4,0)-IF($A11>=DATE(2027,1,4),Loan_Schedule!$B$4,0) -> 375500 | I11: =F11+IF(AND($A11>=Inputs!$B$21,$A11<Inputs!$B$23),Inputs!$B$22,0) -> 375500 | J11: =F11+(Inputs!$B$26/Inputs!$B$25)*(IF($A11>=DATE(2026,10,31),290000,0)+IF($A11>=DATE(2026,11,1),150000,0)+IF($A11>=DATE(2026,11,4),520000,0)) -> 355500 | K11: =G11+IF($A11>=Inputs!$B$21,Inputs!$B$20,0)-IF($A11>=DATE(2026,12,4),Loan_Schedule!$B$4,0)-IF($A11>=DATE(2027,1,4),Loan_Schedule!$B$4,0) -> 351458.63 | L11: =F11+IF($A11>=Inputs!$B$21,Inputs!$B$20,0)-IF($A11>=DATE(2026,11,30),Inputs!$B$20+Loan_Schedule!$B$7,0) -> 375500 | M11: =G11+IF($A11>=Inputs!$B$21,Inputs!$B$20,0)-IF($A11>=DATE(2026,11,30),Inputs!$B$20+Loan_Schedule!$B$7,0) -> 351458.63
A12: =Forecast!A12 -> 46335 | B12: =SUMIFS(Outflows!$E$2:$E$18,Outflows!$B$2:$B$18,$A12,Outflows!$D$2:$D$18,"<>existing_emi_assumed") -> 0 | C12: =SUMIFS(Outflows!$E$2:$E$18,Outflows!$B$2:$B$18,$A12,Outflows!$D$2:$D$18,"existing_emi_assumed") -> 0 | D12: =Forecast!I12 -> 70000 | E12: =Forecast!H12 -> 63994.667 | F12: =F11+D12-B12 -> 245500 | G12: =G11+E12-B12-C12 -> 215453.3 | H12: =F12+IF($A12>=Inputs!$B$21,Inputs!$B$20,0)-IF($A12>=DATE(2026,12,4),Loan_Schedule!$B$4,0)-IF($A12>=DATE(2027,1,4),Loan_Schedule!$B$4,0) -> 445500 | I12: =F12+IF(AND($A12>=Inputs!$B$21,$A12<Inputs!$B$23),Inputs!$B$22,0) -> 445500 | J12: =F12+(Inputs!$B$26/Inputs!$B$25)*(IF($A12>=DATE(2026,10,31),290000,0)+IF($A12>=DATE(2026,11,1),150000,0)+IF($A12>=DATE(2026,11,4),520000,0)) -> 425500 | K12: =G12+IF($A12>=Inputs!$B$21,Inputs!$B$20,0)-IF($A12>=DATE(2026,12,4),Loan_Schedule!$B$4,0)-IF($A12>=DATE(2027,1,4),Loan_Schedule!$B$4,0) -> 415453.3 | L12: =F12+IF($A12>=Inputs!$B$21,Inputs!$B$20,0)-IF($A12>=DATE(2026,11,30),Inputs!$B$20+Loan_Schedule!$B$7,0) -> 445500 | M12: =G12+IF($A12>=Inputs!$B$21,Inputs!$B$20,0)-IF($A12>=DATE(2026,11,30),Inputs!$B$20+Loan_Schedule!$B$7,0) -> 415453.3
A13: =Forecast!A13 -> 46336 | B13: =SUMIFS(Outflows!$E$2:$E$18,Outflows!$B$2:$B$18,$A13,Outflows!$D$2:$D$18,"<>existing_emi_assumed") -> 0 | C13: =SUMIFS(Outflows!$E$2:$E$18,Outflows!$B$2:$B$18,$A13,Outflows!$D$2:$D$18,"existing_emi_assumed") -> 0 | D13: =Forecast!I13 -> 70000 | E13: =Forecast!H13 -> 66386.917 | F13: =F12+D13-B13 -> 315500 | G13: =G12+E13-B13-C13 -> 281840.22 | H13: =F13+IF($A13>=Inputs!$B$21,Inputs!$B$20,0)-IF($A13>=DATE(2026,12,4),Loan_Schedule!$B$4,0)-IF($A13>=DATE(2027,1,4),Loan_Schedule!$B$4,0) -> 515500 | I13: =F13+IF(AND($A13>=Inputs!$B$21,$A13<Inputs!$B$23),Inputs!$B$22,0) -> 515500 | J13: =F13+(Inputs!$B$26/Inputs!$B$25)*(IF($A13>=DATE(2026,10,31),290000,0)+IF($A13>=DATE(2026,11,1),150000,0)+IF($A13>=DATE(2026,11,4),520000,0)) -> 495500 | K13: =G13+IF($A13>=Inputs!$B$21,Inputs!$B$20,0)-IF($A13>=DATE(2026,12,4),Loan_Schedule!$B$4,0)-IF($A13>=DATE(2027,1,4),Loan_Schedule!$B$4,0) -> 481840.22 | L13: =F13+IF($A13>=Inputs!$B$21,Inputs!$B$20,0)-IF($A13>=DATE(2026,11,30),Inputs!$B$20+Loan_Schedule!$B$7,0) -> 515500 | M13: =G13+IF($A13>=Inputs!$B$21,Inputs!$B$20,0)-IF($A13>=DATE(2026,11,30),Inputs!$B$20+Loan_Schedule!$B$7,0) -> 481840.22
A14: =Forecast!A14 -> 46337 | B14: =SUMIFS(Outflows!$E$2:$E$18,Outflows!$B$2:$B$18,$A14,Outflows!$D$2:$D$18,"<>existing_emi_assumed") -> 0 | C14: =SUMIFS(Outflows!$E$2:$E$18,Outflows!$B$2:$B$18,$A14,Outflows!$D$2:$D$18,"existing_emi_assumed") -> 0 | D14: =Forecast!I14 -> 70000 | E14: =Forecast!H14 -> 68091.583 | F14: =F13+D14-B14 -> 385500 | G14: =G13+E14-B14-C14 -> 349931.8 | H14: =F14+IF($A14>=Inputs!$B$21,Inputs!$B$20,0)-IF($A14>=DATE(2026,12,4),Loan_Schedule!$B$4,0)-IF($A14>=DATE(2027,1,4),Loan_Schedule!$B$4,0) -> 585500 | I14: =F14+IF(AND($A14>=Inputs!$B$21,$A14<Inputs!$B$23),Inputs!$B$22,0) -> 585500 | J14: =F14+(Inputs!$B$26/Inputs!$B$25)*(IF($A14>=DATE(2026,10,31),290000,0)+IF($A14>=DATE(2026,11,1),150000,0)+IF($A14>=DATE(2026,11,4),520000,0)) -> 565500 | K14: =G14+IF($A14>=Inputs!$B$21,Inputs!$B$20,0)-IF($A14>=DATE(2026,12,4),Loan_Schedule!$B$4,0)-IF($A14>=DATE(2027,1,4),Loan_Schedule!$B$4,0) -> 549931.8 | L14: =F14+IF($A14>=Inputs!$B$21,Inputs!$B$20,0)-IF($A14>=DATE(2026,11,30),Inputs!$B$20+Loan_Schedule!$B$7,0) -> 585500 | M14: =G14+IF($A14>=Inputs!$B$21,Inputs!$B$20,0)-IF($A14>=DATE(2026,11,30),Inputs!$B$20+Loan_Schedule!$B$7,0) -> 549931.8
... A91: =Forecast!A91 -> 46414 | B91: =SUMIFS(Outflows!$E$2:$E$18,Outflows!$B$2:$B$18,$A91,Outflows!$D$2:$D$18,"<>existing_emi_assumed") -> 0 | C91: =SUMIFS(Outflows!$E$2:$E$18,Outflows!$B$2:$B$18,$A91,Outflows!$D$2:$D$18,"existing_emi_assumed") -> 0 | D91: =Forecast!I91 -> 70000 | E91: =Forecast!H91 -> 68091.583 | F91: =F90+D91-B91 -> 5225500 | G91: =G90+E91-B91-C91 -> 5157036.3 | H91: =F91+IF($A91>=Inputs!$B$21,Inputs!$B$20,0)-IF($A91>=DATE(2026,12,4),Loan_Schedule!$B$4,0)-IF($A91>=DATE(2027,1,4),Loan_Schedule!$B$4,0) -> 5288034.6 | I91: =F91+IF(AND($A91>=Inputs!$B$21,$A91<Inputs!$B$23),Inputs!$B$22,0) -> 5225500 | J91: =F91+(Inputs!$B$26/Inputs!$B$25)*(IF($A91>=DATE(2026,10,31),290000,0)+IF($A91>=DATE(2026,11,1),150000,0)+IF($A91>=DATE(2026,11,4),520000,0)) -> 5405500 | K91: =G91+IF($A91>=Inputs!$B$21,Inputs!$B$20,0)-IF($A91>=DATE(2026,12,4),Loan_Schedule!$B$4,0)-IF($A91>=DATE(2027,1,4),Loan_Schedule!$B$4,0) -> 5219570.9 | L91: =F91+IF($A91>=Inputs!$B$21,Inputs!$B$20,0)-IF($A91>=DATE(2026,11,30),Inputs!$B$20+Loan_Schedule!$B$7,0) -> 5222864.4 | M91: =G91+IF($A91>=Inputs!$B$21,Inputs!$B$20,0)-IF($A91>=DATE(2026,11,30),Inputs!$B$20+Loan_Schedule!$B$7,0) -> 5154400.7

Sheet Loan_Schedule
A1: LENDER EMIs (native PMT formulas; all simulated)
A2: Lender A - bank - 18.5% APR - 3 months - Rs2,00,000
A3: APR (input) | B3: 0.185
A4: Lender A monthly EMI | B4: =PMT(B3/12,3,-200000) -> 68732.704
A5: Lender B - NBFC - 22.0% - 3 months | B5: =PMT(0.22/12,3,-200000) -> 69125.913
A6: Lender C - NBFC - 26.5% - 6 months | B6: =PMT(0.265/12,6,-200000) -> 35956.605
A7: Early-repayment interest estimate (26 days, Lender A) | B7: =Inputs!$B$20*B3*Inputs!$B$19/365 -> 2635.6164
A8: Screen footer terms (Paytm charges nothing, repay early free, UPI AutoPay) are ILLUSTRATIVE deck design copy, not verified lender/Paytm policy.
A9: Amortization - Lender A (contractual 3-month schedule)
A10: month | B10: interest | C10: principal | D10: balance_after
A11: 1 | B11: =200000*$B$3/12 -> 3083.3333 | C11: =$B$4-B11 -> 65649.371 | D11: =200000-C11 -> 134350.63
A12: 2 | B12: =D11*$B$3/12 -> 2071.2389 | C12: =$B$4-B12 -> 66661.466 | D12: =D11-C12 -> 67689.163
A13: 3 | B13: =D12*$B$3/12 -> 1043.5413 | C13: =$B$4-B13 -> 67689.163 | D13: =D12-C13 -> 0
A15: Existing EMI Rs22,000/month: the deck cash plan does not date it. It is INCLUDED in bal_model at an ASSUMED
A16: 1st-of-month due date (editable Inputs B27 - our assumption, not a source fact). bal_story_PARTIAL excludes it
A17: to reproduce the deck narrative faithfully. New-loan EMIs deducted 4 Dec and 4 Jan (3rd, 4 Feb, outside window).

Sheet Policies
A1: OWNER POLICIES (canonical deck values; confirm in product before any live use)
A3: avg daily collections for cap (= Rs19,00,000 / 30, unrounded intermediate) | B3: =Inputs!$B$14/30 -> 63333.333
A4: credit cap per day (8% of avg daily collections) | B4: =B3*Inputs!$B$13 -> 5066.6667
A5: credit cap, monthly equivalent (x30) - exactly Rs1,52,000; screen label Rs1.52 lakh | B5: =B4*30 -> 152000
A6: existing monthly EMI | B6: =Inputs!$B$15 -> 22000
A7: new EMI if Lender A drawdown | B7: =Loan_Schedule!B4 -> 68732.704
A8: total EMIs after drawdown | B8: =B6+B7 -> 90732.704
A9: check: EMIs under monthly cap? | B9: =B8<=B5 -> TRUE
A10: same check, daily-normalized (EMIs/30 <= daily cap) | B10: =B8/30<=B4 -> TRUE
A12: Cross-check: actual trailing-30-day all-channel average from history (plan-period run-rate) | B12: =(SUMIFS(History_DAD!$C$2:$C$548,History_DAD!$A$2:$A$548,">="&(Inputs!$B$4-30))+SUMIFS(History_MAT!$C$2:$C$548,History_MAT!$A$2:$A$548,">="&(Inputs!$B$4-30))+SUMIFS(History_SIO!$C$2:$C$548,History_SIO!$A$2:$A$548,">="&(Inputs!$B$4-30)))/30 -> 70163.467
A13: NOTE: the deck cap uses the stated normal-month average (Rs19L/month); the plan period runs hotter into Diwali.
A15: Owner-only triggers: new payee; changed bank account; drawdowns above Rs50,000; refunds above Rs5,000.
A16: AI check can only stop/escalate, never approve. PIN is simulated. Money moves lender -> supplier directly.

Sheet Options
A1: THREE WAYS TO COVER 5 NOV - two bases shown. Story anchor is PARTIAL (deck bills only); model includes ASSUMED existing EMI.
A3: BASE balances (no action)
A4: story basis (PARTIAL): 4 Nov first negative | B4: =INDEX(Daily_Cash!F2:F91,MATCH(DATE(2026,11,4),Daily_Cash!$A$2:$A$91,0)) -> -145000
A5: story basis: lowest, 5 Nov | B5: =INDEX(Daily_Cash!F2:F91,MATCH(DATE(2026,11,5),Daily_Cash!$A$2:$A$91,0)) -> -184500
A6: story basis: 7 Nov (back above zero) | B6: =INDEX(Daily_Cash!F2:F91,MATCH(DATE(2026,11,7),Daily_Cash!$A$2:$A$91,0)) -> 55500
A7: model basis: 5 Nov | B7: =INDEX(Daily_Cash!G2:G91,MATCH(DATE(2026,11,5),Daily_Cash!$A$2:$A$91,0)) -> -215733.99
A9: Option 1 - Ask Gupta for 15 days on Rs2 lakh (repaid 19 Nov, fee Rs0 if he agrees)
A10: story basis: lowest balance in window | B10: =MIN(Daily_Cash!I2:I91) -> 15500
A11: model basis: balance 5 Nov (deferral in effect) | B11: =INDEX(Daily_Cash!G2:G91,MATCH(DATE(2026,11,5),Daily_Cash!$A$2:$A$91,0))+Inputs!$B$22 -> -15733.992
A12: note: 19 Nov repayment of Rs2,00,000 is absorbed in both bases (balances well above zero by then).
A14: Option 2 - Draw Rs2 lakh on 4 Nov - TWO distinct repayment paths
A15: path A (screen copy): repay IN FULL by 30 Nov
A16: interest estimate (26 days, simple) | B16: =Loan_Schedule!B7 -> 2635.6164
A17: story basis: balance 5 Nov | B17: =INDEX(Daily_Cash!L2:L91,MATCH(DATE(2026,11,5),Daily_Cash!$A$2:$A$91,0)) -> 15500
A18: story basis: 30 Nov after repaying principal + interest | B18: =INDEX(Daily_Cash!L2:L91,MATCH(DATE(2026,11,30),Daily_Cash!$A$2:$A$91,0)) -> 1670864.4
A19: model basis: balance 5 Nov | B19: =INDEX(Daily_Cash!M2:M91,MATCH(DATE(2026,11,5),Daily_Cash!$A$2:$A$91,0)) -> -15733.992
A20: path B (contractual quote): 3 monthly EMIs
A21: EMI (PMT formula) | B21: =Loan_Schedule!B4 -> 68732.704
A22: story basis: balance 5 Nov | B22: =INDEX(Daily_Cash!H2:H91,MATCH(DATE(2026,11,5),Daily_Cash!$A$2:$A$91,0)) -> 15500
A23: story basis: lowest in window (EMIs deducted 4 Dec, 4 Jan) | B23: =MIN(Daily_Cash!H2:H91) -> 15500
A24: model basis: balance 5 Nov | B24: =INDEX(Daily_Cash!K2:K91,MATCH(DATE(2026,11,5),Daily_Cash!$A$2:$A$91,0)) -> -15733.992
A25: NOTE: the drawdown does NOT fix every basis identically - compare rows 17/19 and 22/24.
A27: Option 3 - Buy Rs1.8 lakh less stock - PARTIAL cover, does NOT fully close the 5 Nov gap
A28: Diwali margin at risk (15%) | B28: =Inputs!$B$26*Inputs!$B$18 -> 27000
A29: story basis: residual balance 5 Nov (still negative) | B29: =INDEX(Daily_Cash!J2:J91,MATCH(DATE(2026,11,5),Daily_Cash!$A$2:$A$91,0)) -> -4500
A30: model basis: residual balance 5 Nov (larger shortfall) | B30: =INDEX(Daily_Cash!G2:G91,MATCH(DATE(2026,11,5),Daily_Cash!$A$2:$A$91,0))+Inputs!$B$26 -> -35733.992
